openai_request_runner/__init__.py
openai_request_runner/request_runner.py
openai_request_runner/utils.py
openai_request_runner-0.1.0.dist-info/LICENSE
openai_request_runner-0.1.0.dist-info/METADATA
openai_request_runner-0.1.0.dist-info/WHEEL
openai_request_runner-0.1.0.dist-info/RECORD
