Metadata-Version: 2.1
Name: openai_request_runner
Version: 0.1.0
Summary: Slim Runner for batched OpenAI Requests
Home-page: https://github.com/jphme/openai_request_runner
License: MIT
Author: Jan Philipp Harries
Requires-Python: >=3.9,<4.0
Classifier: Development Status :: 4 - Beta
Classifier: License :: OSI Approved :: MIT License
Classifier: Programming Language :: Python :: 3
Classifier: Programming Language :: Python :: 3.9
Classifier: Programming Language :: Python :: 3.10
Classifier: Programming Language :: Python :: 3.11
Classifier: Programming Language :: Python :: 3.12
Classifier: Topic :: Software Development :: Libraries :: Python Modules
Classifier: Typing :: Typed
Requires-Dist: instructor (>=0.3.1,<0.4.0)
Requires-Dist: openai (>=1.0.0,<2.0.0)
Requires-Dist: pydantic (>=2.0.2,<3.0.0)
Requires-Dist: requests (>=2.26.0,<3.0.0)
Requires-Dist: tiktoken (>=0.3.3,<0.4.0)
Project-URL: Repository, https://github.com/jphme/openai_request_runner
